{
    "Sample Name": "MBPR040_01",
    "Reactor Name": "MB03",
    "Catalyst Type": "Ru/C 5wt.%",
    "Catalyst Amount (mg)": 29.9,
    "Plastic Type": "PE4k Sigma-Aldrich",
    "Plastic Amount (mg)": 299.8,
    "Reaction Temperature (C)": 254,
    "Quench Temperature (C)": 25,
    "Reaction Pressure (psi)": 217,
    "Initial Pressure (psi)": 122,
    "Quench Pressure (psi)": 41,
    "Start Time": "2023-12-01 13:29:00.000",
    "End Time": "2023-12-04 12:43:00.000",
    "Heat Time": 1.2833333333333332,
    "Internal Standard Name": "Benzene, 1,3,5-tri-tert-butyl-",
    "Internal Standard Mass (mg)": 12.2,
    "Reactor Volume (mL)": 13,
    "Remaining solids (mg)": 300.7
}